{
        "jar1": {
            "file": "~/code/craw-redhat-oss/wget/crawl/repo1.maven.org/maven2/org/apache/zookeeper/zookeeper/3.9.1/zookeeper-3.9.1.jar",
            "classcount": 752,
            "md5": "4c02ac252c0b2a2a9ceedfab26772b59",
            "sha1": "63f2b9ad11ee2c26075da446bf58374a61f1e6f0",
            "size": "1 MB",
            "manifest": {
                "Manifest-Version": "1.0",
                "Created-By": "Maven Jar Plugin 3.2.0",
                "Build-Jdk-Spec": "11",
                "Specification-Title": "Apache ZooKeeper - Server",
                "Specification-Version": "3.9",
                "Specification-Vendor": "The Apache Software Foundation",
                "Implementation-Title": "Apache ZooKeeper - Server",
                "Implementation-Version": "3.9.1",
                "Implementation-Vendor": "The Apache Software Foundation",
                "Implementation-Build": "40487256d9b9f274484798758699e49c26d91cda"
            },
            "services": {}
        },
        "jar2": {
            "file": "~/code/craw-redhat-oss/wget/crawl/bfs-dataset/maven-artifacts/org/apache/zookeeper/zookeeper/3.9.1/zookeeper-3.9.1.jar",
            "classcount": 752,
            "md5": "47ed58f45b21291009b8a201b41d7032",
            "sha1": "d880c51bdca0e810b2ace483608c95632c8baf55",
            "size": "1 MB",
            "manifest": {
                "Manifest-Version": "1.0",
                "Created-By": "Maven Jar Plugin 3.2.0",
                "Build-Jdk-Spec": "11",
                "Specification-Title": "Apache ZooKeeper - Server",
                "Specification-Version": "3.9",
                "Specification-Vendor": "The Apache Software Foundation",
                "Implementation-Title": "Apache ZooKeeper - Server",
                "Implementation-Version": "3.9.1",
                "Implementation-Vendor": "The Apache Software Foundation",
                "Implementation-Build": ""
            },
            "services": {}
        },
        "contentset-comparisons": [
            {
                "content-type": "sources",
                "jar1.count": 0,
                "jar2.count": 0,
                "intersection": 0,
                "union": 0,
                "jar1-jar2": [],
                "jar2-jar1": []
            },
            {
                "content-type": "bytecode",
                "jar1.count": 718,
                "jar2.count": 718,
                "intersection": 718,
                "union": 718,
                "jar1-jar2": [],
                "jar2-jar1": []
            },
            {
                "content-type": "metadata",
                "jar1.count": 7,
                "jar2.count": 7,
                "intersection": 7,
                "union": 7,
                "jar1-jar2": [],
                "jar2-jar1": []
            },
            {
                "content-type": "other",
                "jar1.count": 27,
                "jar2.count": 27,
                "intersection": 27,
                "union": 27,
                "jar1-jar2": [],
                "jar2-jar1": []
            }
        ],
        "content-pairwise-comparisons": [{
            "equivalence": {
                "class": "io.github.bineq.equivalences.bytecode.JNormEquivalence2",
                "name": "jnorm2"
            },
            "summary": {
                "description": "comparison results of jar/folder content (pairwise comparison of content in both jars/folders)",
                "equivalent": 716,
                "non-equivalent": 2,
                "errors": 0
            },
            "details": {
                "non-equivalent": [
                    {
                        "class": "org/apache/zookeeper/version/VersionInfoMain.class",
                        "provenance": {
                            "diff-command": "kdiff3 .cache/jnorm2/code/craw-redhat-oss/wget/crawl/repo1.maven.org/maven2/org/apache/zookeeper/zookeeper/3.9.1/zookeeper-3.9.1.jar/org.apache.zookeeper.version.VersionInfoMain.jimple .cache/jnorm2/code/craw-redhat-oss/wget/crawl/bfs-dataset/maven-artifacts/org/apache/zookeeper/zookeeper/3.9.1/zookeeper-3.9.1.jar/org.apache.zookeeper.version.VersionInfoMain.jimple",
                            "transformed-class1": {
                                "value": "public class org.apache.zookeeper.version.VersionInfoMain extends java.lang.Object implements org.ap ..  [abbreviated, 646 chars]",
                                "sha1": "8d25528015db9d10b0452c2236b6ba6d31b5cca4",
                                "cached": ".cache/jnorm2/code/craw-redhat-oss/wget/crawl/repo1.maven.org/maven2/org/apache/zookeeper/zookeeper/3.9.1/zookeeper-3.9.1.jar/org.apache.zookeeper.version.VersionInfoMain.jimple",
                                "md5": "52bd05571c7d92c65223641e1d70fd67"
                            },
                            "transformed-class2": {
                                "value": "public class org.apache.zookeeper.version.VersionInfoMain extends java.lang.Object implements org.ap ..  [abbreviated, 646 chars]",
                                "sha1": "eca6e3e572284e1ebe2de2578bea1c35aa370329",
                                "cached": ".cache/jnorm2/code/craw-redhat-oss/wget/crawl/bfs-dataset/maven-artifacts/org/apache/zookeeper/zookeeper/3.9.1/zookeeper-3.9.1.jar/org.apache.zookeeper.version.VersionInfoMain.jimple",
                                "md5": "38bb936bf9d5ce0c9f1d7e09b41c69d7"
                            }
                        }
                    },
                    {
                        "class": "org/apache/zookeeper/Version.class",
                        "provenance": {
                            "diff-command": "kdiff3 .cache/jnorm2/code/craw-redhat-oss/wget/crawl/repo1.maven.org/maven2/org/apache/zookeeper/zookeeper/3.9.1/zookeeper-3.9.1.jar/org.apache.zookeeper.Version.jimple .cache/jnorm2/code/craw-redhat-oss/wget/crawl/bfs-dataset/maven-artifacts/org/apache/zookeeper/zookeeper/3.9.1/zookeeper-3.9.1.jar/org.apache.zookeeper.Version.jimple",
                            "transformed-class1": {
                                "value": "public class org.apache.zookeeper.Version extends java.lang.Object implements org.apache.zookeeper.v ..  [abbreviated, 5470 chars]",
                                "sha1": "7d1bad104d43192046123a8af04b089ed72dd206",
                                "cached": ".cache/jnorm2/code/craw-redhat-oss/wget/crawl/repo1.maven.org/maven2/org/apache/zookeeper/zookeeper/3.9.1/zookeeper-3.9.1.jar/org.apache.zookeeper.Version.jimple",
                                "md5": "c3ed2a557115cb47133d18892d6da13d"
                            },
                            "transformed-class2": {
                                "value": "public class org.apache.zookeeper.Version extends java.lang.Object implements org.apache.zookeeper.v ..  [abbreviated, 5449 chars]",
                                "sha1": "c55322f2024f83399fb97a5fd9c1ccddc55f219a",
                                "cached": ".cache/jnorm2/code/craw-redhat-oss/wget/crawl/bfs-dataset/maven-artifacts/org/apache/zookeeper/zookeeper/3.9.1/zookeeper-3.9.1.jar/org.apache.zookeeper.Version.jimple",
                                "md5": "cd0bf25e306f17b970be9f3ce868d281"
                            }
                        }
                    }
                ],
                "errors": []
            }
        }]
    }